README.rst
setup.py
tvdbsimple/__init__.py
tvdbsimple/base.py
tvdbsimple/episode.py
tvdbsimple/keys.py
tvdbsimple/languages.py
tvdbsimple/search.py
tvdbsimple/series.py
tvdbsimple/updates.py
tvdbsimple/user.py
tvdbsimple.egg-info/PKG-INFO
tvdbsimple.egg-info/SOURCES.txt
tvdbsimple.egg-info/dependency_links.txt
tvdbsimple.egg-info/requires.txt
tvdbsimple.egg-info/top_level.txt