Metadata-Version: 1.1
Name: tvdbsimple
Version: 1.0.6
Summary: A Python wrapper for TheTVDb Database API v2
Home-page: https://github.com/phate89/tvdbsimple
Author: phate89
Author-email: phates89@gmail.com
License: GPLv3
Download-URL: https://github.com/phate89/tvdbsimple/tarball/1.0.6
Keywords: show series seasons tv database tvdb wrapper thetvdb api
Platform: UNKNOWN
Classifier: Development Status :: 5 - Production/Stable
Classifier: Intended Audience :: Developers
Classifier: Operating System :: OS Independent
Classifier: Programming Language :: Python :: 2.7
Classifier: Programming Language :: Python :: 3.3
Classifier: Programming Language :: Python :: 3.4
Classifier: Programming Language :: Python :: 3.5
Classifier: Programming Language :: Python :: 3.6
Classifier: Programming Language :: Python :: 3.7
Classifier: Topic :: Utilities
